p2pclient/__init__.py
p2pclient/_version.py
p2pclient/config.py
p2pclient/connmgr.py
p2pclient/control.py
p2pclient/daemon.py
p2pclient/datastructures.py
p2pclient/dht.py
p2pclient/exceptions.py
p2pclient/p2pclient.py
p2pclient/pubsub.py
p2pclient/serialization.py
p2pclient/utils.py
p2pclient/libp2p_stubs/__init__.py
p2pclient/libp2p_stubs/crypto/__init__.py
p2pclient/libp2p_stubs/crypto/keys.py
p2pclient/libp2p_stubs/crypto/rsa.py
p2pclient/libp2p_stubs/crypto/pb/__init__.py
p2pclient/libp2p_stubs/crypto/pb/crypto_pb2.py
p2pclient/libp2p_stubs/peer/__init__.py
p2pclient/libp2p_stubs/peer/id.py
p2pclient/libp2p_stubs/peer/peerinfo.py
p2pclient/pb/__init__.py
p2pclient/pb/p2pd_pb2.py
p2pclient-0.2.0.dist-info/LICENSE
p2pclient-0.2.0.dist-info/METADATA
p2pclient-0.2.0.dist-info/WHEEL
p2pclient-0.2.0.dist-info/top_level.txt
p2pclient-0.2.0.dist-info/RECORD
